odoo8_addon_auth_dynamic_groups-8.0.1.0.0.99.dev21-py2.7-nspkg.pth
odoo8_addon_auth_dynamic_groups-8.0.1.0.0.99.dev21.dist-info/METADATA
odoo8_addon_auth_dynamic_groups-8.0.1.0.0.99.dev21.dist-info/RECORD
odoo8_addon_auth_dynamic_groups-8.0.1.0.0.99.dev21.dist-info/WHEEL
odoo8_addon_auth_dynamic_groups-8.0.1.0.0.99.dev21.dist-info/namespace_packages.txt
odoo8_addon_auth_dynamic_groups-8.0.1.0.0.99.dev21.dist-info/top_level.txt
odoo_addons/auth_dynamic_groups/README.rst
odoo_addons/auth_dynamic_groups/__init__.py
odoo_addons/auth_dynamic_groups/__openerp__.py
odoo_addons/auth_dynamic_groups/i18n/ar.po
odoo_addons/auth_dynamic_groups/i18n/auth_dynamic_groups.pot
odoo_addons/auth_dynamic_groups/i18n/ca.po
odoo_addons/auth_dynamic_groups/i18n/da.po
odoo_addons/auth_dynamic_groups/i18n/de.po
odoo_addons/auth_dynamic_groups/i18n/el_GR.po
odoo_addons/auth_dynamic_groups/i18n/es.po
odoo_addons/auth_dynamic_groups/i18n/es_ES.po
odoo_addons/auth_dynamic_groups/i18n/fi.po
odoo_addons/auth_dynamic_groups/i18n/fr.po
odoo_addons/auth_dynamic_groups/i18n/fr_CH.po
odoo_addons/auth_dynamic_groups/i18n/hr.po
odoo_addons/auth_dynamic_groups/i18n/hr_HR.po
odoo_addons/auth_dynamic_groups/i18n/it.po
odoo_addons/auth_dynamic_groups/i18n/nl.po
odoo_addons/auth_dynamic_groups/i18n/pt_BR.po
odoo_addons/auth_dynamic_groups/i18n/sl.po
odoo_addons/auth_dynamic_groups/i18n/tr.po
odoo_addons/auth_dynamic_groups/i18n/tr_TR.po
odoo_addons/auth_dynamic_groups/i18n/zh_CN.po
odoo_addons/auth_dynamic_groups/model/__init__.py
odoo_addons/auth_dynamic_groups/model/res_groups.py
odoo_addons/auth_dynamic_groups/model/res_users.py
odoo_addons/auth_dynamic_groups/static/description/icon.png
odoo_addons/auth_dynamic_groups/view/res_groups.xml
